{
  "ReRoutes": [
    {
      "DownstreamPathTemplate": "/api/task",
      "DownstreamScheme": "http",
      "DownstreamHostAndPorts": [
        {
          "Host": "task-mic",
          "Port": 80
        }
      ],
      "UpstreamPathTemplate": "/api/task",
      "UpstreamHttpMethod": [ "Get" ],
      "AuthenticationOptions": {
        "AuthenticationProviderKey": "Bearer",
        "AllowedScopes": []
      }
    },
    {
      "DownstreamPathTemplate": "/api/task/{everything}",
      "DownstreamScheme": "http",
      "DownstreamHostAndPorts": [
        {
          "Host": "task-mic",
          "Port": 80
        }
      ],
      "UpstreamPathTemplate": "/api/task/{everything}",
      "UpstreamHttpMethod": [ "Post", "Delete", "Options" ],
      "AuthenticationOptions": {
        "AuthenticationProviderKey": "Bearer",
        "AllowedScopes": []
      },
      "RouteClaimsRequirement": {
        "Role": "Administrator"
      }
    },
    {
      "DownstreamPathTemplate": "/api/widget",
      "DownstreamScheme": "http",
      "DownstreamHostAndPorts": [
        {
          "Host": "widget-mic",
          "Port": 80
        }
      ],
      "UpstreamPathTemplate": "/api/widget",
      "UpstreamHttpMethod": [ "Get" ],
      "AuthenticationOptions": {
        "AuthenticationProviderKey": "Bearer",
        "AllowedScopes": []
      }
    },
    {
      "DownstreamPathTemplate": "/api/widget/{everything}",
      "DownstreamScheme": "http",
      "DownstreamHostAndPorts": [
        {
          "Host": "widget-mic",
          "Port": 80
        }
      ],
      "UpstreamPathTemplate": "/api/widget/{everything}",
      "UpstreamHttpMethod": [ "Post", "Delete", "Options" ],
      "AuthenticationOptions": {
        "AuthenticationProviderKey": "Bearer",
        "AllowedScopes": []
      },
      "RouteClaimsRequirement": {
        "Role": "Administrator"
      }
    },
    {
      "DownstreamPathTemplate": "/api/log/client",
      "DownstreamScheme": "http",
      "DownstreamHostAndPorts": [
        {
          "Host": "log-mic",
          "Port": 80
        }
      ],
      "UpstreamPathTemplate": "/api/log/client",
      "UpstreamHttpMethod": [ "Post", "Options" ]
    }
  ],
  "GlobalConfiguration": {
    "RequestIdKey": "OcRequestId",
    "AdministrationPath": "/administration"
  }
}
